discordemoji/__init__.py
discordemoji/main.py
discordemoji/resources/__init__.py
discordemoji/resources/dictionaries.py
tests/__init__.py
tests/tests.py
discordemoji-0.0.1.dist-info/LICENSE
discordemoji-0.0.1.dist-info/METADATA
discordemoji-0.0.1.dist-info/WHEEL
discordemoji-0.0.1.dist-info/top_level.txt
discordemoji-0.0.1.dist-info/RECORD
